echoices/__init__.py
echoices/enums/__init__.py
echoices/enums/enums.py
echoices/fields/__init__.py
echoices/fields/fields.py
echoices/forms/__init__.py
echoices/forms/forms.py
echoices/locale/en/LC_MESSAGES/django.po
echoices/locale/fr/LC_MESSAGES/django.po
echoices/tests/__init__.py
echoices/tests/__main__.py
echoices/tests/admin.py
echoices/tests/models.py
echoices/tests/settings.py
echoices/tests/tests.py
echoices/tests/urls.py
django_echoices-2.8.0.dist-info/LICENSE
django_echoices-2.8.0.dist-info/METADATA
django_echoices-2.8.0.dist-info/WHEEL
django_echoices-2.8.0.dist-info/top_level.txt
django_echoices-2.8.0.dist-info/RECORD
