Metadata-Version: 2.1
Name: django-echoices
Version: 2.8.0
Summary: Choices for Django model fields as enumeration
Home-page: https://github.com/mbourqui/django-echoices/
Author: Marc Bourqui
Author-email: pypi.kemar@bourqui.org
License: GNU GPLv3
Download-URL: https://github.com/mbourqui/django-echoices/releases/tag/v2.8.0
Keywords: django choices models enum
Platform: UNKNOWN
Classifier: Development Status :: 5 - Production/Stable
Classifier: Environment :: Web Environment
Classifier: Framework :: Django
Classifier: Framework :: Django :: 1.11
Classifier: Framework :: Django :: 2.2
Classifier: Framework :: Django :: 3.0
Classifier: Intended Audience :: Developers
Classifier: License :: OSI Approved :: GNU General Public License v3 (GPLv3)
Classifier: Operating System :: OS Independent
Classifier: Programming Language :: Python
Classifier: Programming Language :: Python :: 3
Classifier: Programming Language :: Python :: 3.5
Classifier: Programming Language :: Python :: 3.6
Classifier: Programming Language :: Python :: 3.7
Classifier: Programming Language :: Python :: 3.8
Classifier: Topic :: Internet :: WWW/HTTP
Classifier: Topic :: Internet :: WWW/HTTP :: Dynamic Content
Classifier: Topic :: Utilities
Requires-Dist: django (<3.0,>=1.11.29)
